mosaicpy/__init__.py
mosaicpy/mosaic.py
mosaicpy-0.0.1.dist-info/LICENSE
mosaicpy-0.0.1.dist-info/METADATA
mosaicpy-0.0.1.dist-info/WHEEL
mosaicpy-0.0.1.dist-info/top_level.txt
mosaicpy-0.0.1.dist-info/RECORD
