Metadata-Version: 2.1
Name: mosaicpy
Version: 0.0.1
Summary: Access the Modern Ocean Sediment Archive and Inventory of Carbon database
Author-email: Sarah Paradis <sparadis@ethz.ch>
License: MIT License
Project-URL: Homepage, https://mosaic.ethz.ch
Keywords: database,carbon,marine sediments,earth science,open data
Classifier: License :: OSI Approved :: MIT License
Classifier: Programming Language :: Python
Classifier: Programming Language :: Python :: 3
License-File: LICENSE
Requires-Dist: requests
Requires-Dist: pandas
